lisptick/__init__.py
lisptick/classes.py
lisptick/exceptions.py
lisptick/reader.py
lisptick/types.py
lisptick-0.1.0.dist-info/LICENSE
lisptick-0.1.0.dist-info/METADATA
lisptick-0.1.0.dist-info/WHEEL
lisptick-0.1.0.dist-info/top_level.txt
lisptick-0.1.0.dist-info/RECORD
