Metadata-Version: 2.1
Name: lisptick
Version: 0.1.0
Summary: LispTick Python client library
Home-page: https://github.com/kereon-intelligence/lisptick-client
Author: Cedric Joulain
Author-email: cedric.joulain@kereon-intelligence.com
License: UNKNOWN
Project-URL: Bug Tracker, https://github.com/kereon-intelligence/lisptick-client/issues
Platform: UNKNOWN
Classifier: License :: OSI Approved :: Apache Software License
Classifier: Operating System :: OS Independent
Classifier: Programming Language :: Python
Requires-Python: >=2.6
License-File: LICENSE
